calapi/__init__.py
calapi/acl.py
calapi/calendarlist.py
calapi/calendars.py
calapi/calendarsettings.py
calapi/colors.py
calapi/events.py
calapi/exceptions.py
calapi/oauth.py
calapi/query.py
calapi/service.py
calapi/session.py
calapi-1.0.0.dist-info/METADATA
calapi-1.0.0.dist-info/WHEEL
calapi-1.0.0.dist-info/top_level.txt
calapi-1.0.0.dist-info/RECORD
